[    
      {
        "socialid": "1",    
        "id": "1",
        "name": "FACEBOOK",
        "username": "ITURUU"
      },
      {
        "socialid": "1",    
        "id": "2",
        "name": "INSTAGRAM",
        "username": "ENKHTUR78"
      },
      {
        "socialid": "1",    
        "id": "3",
        "name": "SNAPCHAT",
        "username": "TURUU8899"
      },
      {
        "socialid": "1",    
        "id": "4",
        "name": "TWITTER",
        "username": "ITURUU_TWITTER"
      }
]  
